[
  {
    "wind_mph": 3.93,
    "gust_mph": 2.99,
    "temp_c": 18.9,
    "precip_pct": 0.0,
    "delta_strokes": 0.0,
    "weathercode": 0,
    "round": 1
  },
  {
    "wind_mph": 4.05,
    "gust_mph": 3.73,
    "temp_c": 19.8,
    "precip_pct": 0.0,
    "delta_strokes": 0.0,
    "weathercode": 0,
    "round": 2
  },
  {
    "wind_mph": 4.5,
    "gust_mph": 4.36,
    "temp_c": 19.6,
    "precip_pct": 0.0,
    "delta_strokes": 0.0,
    "weathercode": 3,
    "round": 3
  },
  {
    "wind_mph": 3.85,
    "gust_mph": 3.65,
    "temp_c": 17.4,
    "precip_pct": 0.0,
    "delta_strokes": 0.0,
    "weathercode": 2,
    "round": 4
  }
]